injection/__init__.py
injection/__version__.py
injection/auto_inject.py
injection/base_container.py
injection/exceptions.py
injection/inject.py
injection/provide.py
injection/provided.py
injection/resolving.py
injection/providers/__init__.py
injection/providers/base.py
injection/providers/base_factory.py
injection/providers/coroutine.py
injection/providers/factory.py
injection/providers/object.py
injection/providers/resource.py
injection/providers/singleton.py
injection/providers/transient.py
deps_injection-1.8.1.dist-info/METADATA
deps_injection-1.8.1.dist-info/WHEEL
deps_injection-1.8.1.dist-info/licenses/LICENSE
deps_injection-1.8.1.dist-info/RECORD
