Metadata-Version: 2.4
Name: deps-injection
Version: 1.8.1
Summary: Easy dependency injection without wiring
Project-URL: Homepage, https://pypi.org/project/deps-injection/
Project-URL: Issues, https://github.com/nightblure/injection/issues?q=is%3Aissue+is%3Aopen+sort%3Aupdated-desc
Project-URL: Changelog, https://github.com/nightblure/injection/releases
Project-URL: Documentation, https://injection.readthedocs.io/latest/
Project-URL: Repository, https://github.com/nightblure/injection.git
Author-email: Ivan Belyaev <vanobel159@gmail.com>
License: MIT
License-File: LICENSE
Keywords: dependency,di,injection,injector
Classifier: Programming Language :: Python
Classifier: Programming Language :: Python :: 3.8
Classifier: Programming Language :: Python :: 3.9
Classifier: Programming Language :: Python :: 3.10
Classifier: Programming Language :: Python :: 3.11
Classifier: Programming Language :: Python :: 3.12
Classifier: Programming Language :: Python :: 3.13
Classifier: Programming Language :: Python :: Implementation :: CPython
Requires-Python: >=3.8
Requires-Dist: typing-extensions>=4.12.2
